mdmaker/__init__.py
mdmaker/helpers.py
mdmaker/mdmaker.py
mdmaker-0.0.2.dist-info/LICENSE
mdmaker-0.0.2.dist-info/METADATA
mdmaker-0.0.2.dist-info/WHEEL
mdmaker-0.0.2.dist-info/top_level.txt
mdmaker-0.0.2.dist-info/RECORD
