Metadata-Version: 2.1
Name: mdmaker
Version: 0.0.2
Summary: Generate Markdown files with Python
Author-email: Hypersport <boss.yuan@outlook.com>
License: MIT License
Project-URL: Homepage, https://github.com/hypersport/Markdown-Generator
Project-URL: Bug Tracker, https://github.com/hypersport/Markdown-Generator/issues
Keywords: Markdown,Generator
Classifier: Programming Language :: Python :: 3
Classifier: License :: OSI Approved :: MIT License
Classifier: Operating System :: OS Independent
Requires-Python: >=3.7
License-File: LICENSE
